{
  "object": [
    [
      0.3831895970573359,
      -0.060553871027277814,
      1.2862432228719365
    ],
    [
      0.18603917512200568,
      -0.06682171508809594,
      -0.3315882392393663,
      0.9224822617865049
    ]
  ],
  "arm": [
    [
      0.0,
      0.0,
      1.25
    ],
    [
      0.0,
      0.0,
      0.0,
      1.0
    ]
  ],
  "joints": [
    [
      0.08355060488712128,
      1.3817072486155269e-15,
      [
        0.0,
        0.0,
        0.0,
        0.0,
        0.0,
        0.0
      ],
      1.91253263226443e-15
    ],
    [
      -0.5657689728022981,
      1.2774503677093207e-14,
      [
        0.0,
        0.0,
        0.0,
        0.0,
        0.0,
        0.0
      ],
      -8.653699721631163
    ],
    [
      -0.1968050551671889,
      0.0,
      [
        0.0,
        0.0,
        0.0,
        0.0,
        0.0,
        0.0
      ],
      2.123802150935075
    ],
    [
      -2.178890455471285,
      5.259681579161679e-14,
      [
        0.0,
        0.0,
        0.0,
        0.0,
        0.0,
        0.0
      ],
      19.517256682101728
    ],
    [
      -0.10508135210673686,
      -1.6514567491299204e-15,
      [
        0.0,
        0.0,
        0.0,
        0.0,
        0.0,
        0.0
      ],
      1.1757898095008565
    ],
    [
      1.6241614349368534,
      -2.5396351688300456e-14,
      [
        0.0,
        0.0,
        0.0,
        0.0,
        0.0,
        0.0
      ],
      1.5589689336558101
    ],
    [
      0.016724578823637946,
      3.7470027081099033e-16,
      [
        0.0,
        0.0,
        0.0,
        0.0,
        0.0,
        0.0
      ],
      1.2415332336420531e-09
    ],
    [
      0.0,
      0.0,
      [
        0.0,
        0.0,
        0.0,
        0.0,
        0.0,
        0.0
      ],
      0.0
    ],
    [
      0.0,
      0.0,
      [
        0.0,
        0.0,
        0.0,
        0.0,
        0.0,
        0.0
      ],
      0.0
    ],
    [
      -2.1069131283254584e-07,
      0.0,
      [
        0.0,
        0.0,
        0.0,
        0.0,
        0.0,
        0.0
      ],
      -0.9610011053782832
    ],
    [
      4.654782730104503e-07,
      4.336808689942018e-19,
      [
        0.0,
        0.0,
        0.0,
        0.0,
        0.0,
        0.0
      ],
      -0.0016824217816008204
    ],
    [
      0.0,
      0.0,
      [
        0.0,
        0.0,
        0.0,
        0.0,
        0.0,
        0.0
      ],
      0.0
    ]
  ],
  "seed": 2,
  "task": "grasping_simp"
}