{
  "object": [
    [
      0.35099350628055037,
      7.627295522854395e-05,
      1.267336291847561
    ],
    [
      -0.0017478846338212911,
      -0.003029645946159837,
      0.9224427727631179,
      0.38611798342195647
    ]
  ],
  "arm": [
    [
      0.0,
      0.0,
      1.25
    ],
    [
      0.0,
      0.0,
      0.0,
      1.0
    ]
  ],
  "joints": [
    [
      -0.020275914968632392,
      4.0700949555105836e-16,
      [
        0.0,
        0.0,
        0.0,
        0.0,
        0.0,
        0.0
      ],
      -3.3176586478056436e-16
    ],
    [
      -0.6578899689724831,
      1.292022044907526e-14,
      [
        0.0,
        0.0,
        0.0,
        0.0,
        0.0,
        0.0
      ],
      -6.442780175760008
    ],
    [
      0.007326238581169594,
      -1.0408340855860843e-16,
      [
        0.0,
        0.0,
        0.0,
        0.0,
        0.0,
        0.0
      ],
      -0.7015669599257106
    ],
    [
      -2.30315847479385,
      4.7128967395337895e-14,
      [
        0.0,
        0.0,
        0.0,
        0.0,
        0.0,
        0.0
      ],
      19.726257573089335
    ],
    [
      0.005231755262381764,
      -9.367506770274758e-17,
      [
        0.0,
        0.0,
        0.0,
        0.0,
        0.0,
        0.0
      ],
      1.1750907062006972
    ],
    [
      1.6490933768118974,
      -2.4868995751603507e-14,
      [
        0.0,
        0.0,
        0.0,
        0.0,
        0.0,
        0.0
      ],
      1.561114978080295
    ],
    [
      0.5098198879178362,
      1.3047614204342306e-14,
      [
        0.0,
        0.0,
        0.0,
        0.0,
        0.0,
        0.0
      ],
      1.1286479965801343e-08
    ],
    [
      0.0,
      0.0,
      [
        0.0,
        0.0,
        0.0,
        0.0,
        0.0,
        0.0
      ],
      0.0
    ],
    [
      0.0,
      0.0,
      [
        0.0,
        0.0,
        0.0,
        0.0,
        0.0,
        0.0
      ],
      0.0
    ],
    [
      -9.398641482397065e-07,
      0.0,
      [
        0.0,
        0.0,
        0.0,
        0.0,
        0.0,
        0.0
      ],
      -0.35048190196622275
    ],
    [
      2.033433962864098e-06,
      0.0,
      [
        0.0,
        0.0,
        0.0,
        0.0,
        0.0,
        0.0
      ],
      -0.00032137562391751666
    ],
    [
      0.0,
      0.0,
      [
        0.0,
        0.0,
        0.0,
        0.0,
        0.0,
        0.0
      ],
      0.0
    ]
  ],
  "seed": 9,
  "task": "grasping_simp"
}