{
  "object": [
    [
      0.4010128825945549,
      -0.055729116145761634,
      1.2667062209775495
    ],
    [
      -0.7024035747487078,
      -0.08087141978520605,
      0.702529079495274,
      -0.08088216185095659
    ]
  ],
  "arm": [
    [
      0.0,
      0.0,
      1.25
    ],
    [
      0.0,
      0.0,
      0.0,
      1.0
    ]
  ],
  "joints": [
    [
      -0.021754264956860368,
      3.9207461062507054e-16,
      [
        0.0,
        0.0,
        0.0,
        0.0,
        0.0,
        0.0
      ],
      -3.4932993997482953e-15
    ],
    [
      -0.5716741130176985,
      1.2351231148954867e-14,
      [
        0.0,
        0.0,
        0.0,
        0.0,
        0.0,
        0.0
      ],
      -8.94948235857967
    ],
    [
      -0.047760071426666995,
      -8.326672684688674e-16,
      [
        0.0,
        0.0,
        0.0,
        0.0,
        0.0,
        0.0
      ],
      0.11467018670381389
    ],
    [
      -2.2354830676127824,
      5.132005931329786e-14,
      [
        0.0,
        0.0,
        0.0,
        0.0,
        0.0,
        0.0
      ],
      19.784664607491646
    ],
    [
      -0.02541691986023177,
      -3.608224830031759e-16,
      [
        0.0,
        0.0,
        0.0,
        0.0,
        0.0,
        0.0
      ],
      1.1728670467624562
    ],
    [
      1.6683029083747978,
      -2.4369395390522186e-14,
      [
        0.0,
        0.0,
        0.0,
        0.0,
        0.0,
        0.0
      ],
      1.561440819009679
    ],
    [
      0.45322334664788444,
      6.140921104957897e-15,
      [
        0.0,
        0.0,
        0.0,
        0.0,
        0.0,
        0.0
      ],
      1.1346833074776233e-08
    ],
    [
      0.0,
      0.0,
      [
        0.0,
        0.0,
        0.0,
        0.0,
        0.0,
        0.0
      ],
      0.0
    ],
    [
      0.0,
      0.0,
      [
        0.0,
        0.0,
        0.0,
        0.0,
        0.0,
        0.0
      ],
      0.0
    ],
    [
      -9.236517367688087e-07,
      0.0,
      [
        0.0,
        0.0,
        0.0,
        0.0,
        0.0,
        0.0
      ],
      -0.4316988592877669
    ],
    [
      1.997821092845109e-06,
      -4.336808689942018e-19,
      [
        0.0,
        0.0,
        0.0,
        0.0,
        0.0,
        0.0
      ],
      -0.00079257731625916
    ],
    [
      0.0,
      0.0,
      [
        0.0,
        0.0,
        0.0,
        0.0,
        0.0,
        0.0
      ],
      0.0
    ]
  ],
  "seed": 4,
  "task": "grasping_simp"
}