{
  "object": [
    [
      0.4043416955287961,
      0.021881330351968112,
      1.2670386326063587
    ],
    [
      -0.01639337553280587,
      0.005629827633690159,
      0.9512021899215155,
      0.3080810870014069
    ]
  ],
  "arm": [
    [
      0.0,
      0.0,
      1.25
    ],
    [
      0.0,
      0.0,
      0.0,
      1.0
    ]
  ],
  "joints": [
    [
      0.07625958447568885,
      1.6078176116873788e-15,
      [
        0.0,
        0.0,
        0.0,
        0.0,
        0.0,
        0.0
      ],
      1.286405877654051e-15
    ],
    [
      -0.47435669356265564,
      5.4262150328554526e-15,
      [
        0.0,
        0.0,
        0.0,
        0.0,
        0.0,
        0.0
      ],
      -11.889069074905219
    ],
    [
      -0.032762047872800855,
      0.0,
      [
        0.0,
        0.0,
        0.0,
        0.0,
        0.0,
        0.0
      ],
      -0.06552916516710315
    ],
    [
      -2.174126480644925,
      4.599098879509711e-14,
      [
        0.0,
        0.0,
        0.0,
        0.0,
        0.0,
        0.0
      ],
      19.89654326648134
    ],
    [
      -0.01500972992924841,
      -1.5612511283791264e-16,
      [
        0.0,
        0.0,
        0.0,
        0.0,
        0.0,
        0.0
      ],
      1.167508651312836
    ],
    [
      1.7027583594973095,
      -2.3564483697668948e-14,
      [
        0.0,
        0.0,
        0.0,
        0.0,
        0.0,
        0.0
      ],
      1.5593850745413158
    ],
    [
      0.3863260778669472,
      6.048113398993138e-15,
      [
        0.0,
        0.0,
        0.0,
        0.0,
        0.0,
        0.0
      ],
      6.930283813862863e-09
    ],
    [
      0.0,
      0.0,
      [
        0.0,
        0.0,
        0.0,
        0.0,
        0.0,
        0.0
      ],
      0.0
    ],
    [
      0.0,
      0.0,
      [
        0.0,
        0.0,
        0.0,
        0.0,
        0.0,
        0.0
      ],
      0.0
    ],
    [
      -8.601565316530318e-07,
      0.0,
      [
        0.0,
        0.0,
        0.0,
        0.0,
        0.0,
        0.0
      ],
      -0.5271841820887173
    ],
    [
      1.860698138517162e-06,
      -4.336808689942018e-19,
      [
        0.0,
        0.0,
        0.0,
        0.0,
        0.0,
        0.0
      ],
      -0.0009912629605261162
    ],
    [
      0.0,
      0.0,
      [
        0.0,
        0.0,
        0.0,
        0.0,
        0.0,
        0.0
      ],
      0.0
    ]
  ],
  "seed": 0,
  "task": "grasping_simp"
}