{
  "object": [
    [
      0.39181267504046036,
      0.02191392934926529,
      1.2661128409809548
    ],
    [
      0.005279867299974395,
      -0.0014414852497546596,
      0.7068416980575415,
      0.707350591297343
    ]
  ],
  "arm": [
    [
      0.0,
      0.0,
      1.25
    ],
    [
      0.0,
      0.0,
      0.0,
      1.0
    ]
  ],
  "joints": [
    [
      0.017841964562536543,
      3.371868756429919e-16,
      [
        0.0,
        0.0,
        0.0,
        0.0,
        0.0,
        0.0
      ],
      -7.708677446371937e-16
    ],
    [
      -0.5593892528878193,
      1.1123046927963287e-14,
      [
        0.0,
        0.0,
        0.0,
        0.0,
        0.0,
        0.0
      ],
      -9.261539514690742
    ],
    [
      0.014048224444876488,
      0.0,
      [
        0.0,
        0.0,
        0.0,
        0.0,
        0.0,
        0.0
      ],
      -0.6997377319463853
    ],
    [
      -2.21991398004561,
      -4.7656323332034844e-14,
      [
        0.0,
        0.0,
        0.0,
        0.0,
        0.0,
        0.0
      ],
      19.777975586965287
    ],
    [
      0.007573266115234588,
      -9.194034422677078e-17,
      [
        0.0,
        0.0,
        0.0,
        0.0,
        0.0,
        0.0
      ],
      1.172599535676566
    ],
    [
      1.6624967636631363,
      -2.5590640717609858e-14,
      [
        0.0,
        0.0,
        0.0,
        0.0,
        0.0,
        0.0
      ],
      1.5579451766084818
    ],
    [
      0.7044181157712882,
      1.1774544013409827e-14,
      [
        0.0,
        0.0,
        0.0,
        0.0,
        0.0,
        0.0
      ],
      8.278025739146997e-09
    ],
    [
      0.0,
      0.0,
      [
        0.0,
        0.0,
        0.0,
        0.0,
        0.0,
        0.0
      ],
      0.0
    ],
    [
      0.0,
      0.0,
      [
        0.0,
        0.0,
        0.0,
        0.0,
        0.0,
        0.0
      ],
      0.0
    ],
    [
      -1.384818688642842e-06,
      -4.336808689942018e-19,
      [
        0.0,
        0.0,
        0.0,
        0.0,
        0.0,
        0.0
      ],
      -0.05918019922922025
    ],
    [
      2.985245061320084e-06,
      1.3010426069826053e-18,
      [
        0.0,
        0.0,
        0.0,
        0.0,
        0.0,
        0.0
      ],
      -6.712665894932374e-05
    ],
    [
      0.0,
      0.0,
      [
        0.0,
        0.0,
        0.0,
        0.0,
        0.0,
        0.0
      ],
      0.0
    ]
  ],
  "seed": 1,
  "task": "grasping_simp"
}