{
  "object": [
    [
      0.39181267504046036,
      0.02191392934926529,
      1.2661128409809548
    ],
    [
      0.005279867299974395,
      -0.0014414852497546596,
      0.7068416980575415,
      0.707350591297343
    ]
  ],
  "arm": [
    [
      0.0,
      0.0,
      1.25
    ],
    [
      0.0,
      0.0,
      0.0,
      1.0
    ]
  ],
  "joints": [
    [
      -0.023211428317570098,
      3.668940151690947e-16,
      [
        0.0,
        0.0,
        0.0,
        0.0,
        0.0,
        0.0
      ],
      -3.8380756905986857e-16
    ],
    [
      -0.5808226365392156,
      1.1705914015891494e-14,
      [
        0.0,
        0.0,
        0.0,
        0.0,
        0.0,
        0.0
      ],
      -8.648287732020712
    ],
    [
      0.03395831112363348,
      0.0,
      [
        0.0,
        0.0,
        0.0,
        0.0,
        0.0,
        0.0
      ],
      -0.9907701591661764
    ],
    [
      -2.2486624623435096,
      -4.263256414560601e-14,
      [
        0.0,
        0.0,
        0.0,
        0.0,
        0.0,
        0.0
      ],
      19.8015887810589
    ],
    [
      0.018890781759961398,
      -3.712308238590367e-16,
      [
        0.0,
        0.0,
        0.0,
        0.0,
        0.0,
        0.0
      ],
      1.1718979644742997
    ],
    [
      1.6698080361430656,
      -2.400857290751901e-14,
      [
        0.0,
        0.0,
        0.0,
        0.0,
        0.0,
        0.0
      ],
      1.5575926164365328
    ],
    [
      0.8624126060505605,
      1.2132439150547292e-14,
      [
        0.0,
        0.0,
        0.0,
        0.0,
        0.0,
        0.0
      ],
      7.748707123739359e-09
    ],
    [
      0.0,
      0.0,
      [
        0.0,
        0.0,
        0.0,
        0.0,
        0.0,
        0.0
      ],
      0.0
    ],
    [
      0.0,
      0.0,
      [
        0.0,
        0.0,
        0.0,
        0.0,
        0.0,
        0.0
      ],
      0.0
    ],
    [
      -1.4714522525505295e-06,
      -3.0357660829594124e-18,
      [
        0.0,
        0.0,
        0.0,
        0.0,
        0.0,
        0.0
      ],
      -0.0007444664380326627
    ],
    [
      3.168324209895718e-06,
      3.0357660829594124e-18,
      [
        0.0,
        0.0,
        0.0,
        0.0,
        0.0,
        0.0
      ],
      0.0002967410627859133
    ],
    [
      0.0,
      0.0,
      [
        0.0,
        0.0,
        0.0,
        0.0,
        0.0,
        0.0
      ],
      0.0
    ]
  ],
  "seed": 1,
  "task": "grasping_simp"
}