{
  "object": [
    [
      0.43959487264788694,
      -0.016263632849484514,
      1.2756278029240302
    ],
    [
      0.0012170999672709935,
      0.007578335118365746,
      0.5980825776369996,
      0.801397727618182
    ]
  ],
  "arm": [
    [
      0.0,
      0.0,
      1.25
    ],
    [
      0.0,
      0.0,
      0.0,
      1.0
    ]
  ],
  "joints": [
    [
      -0.4644377453473444,
      -5.223252386166166e-15,
      [
        0.0,
        0.0,
        0.0,
        0.0,
        0.0,
        0.0
      ],
      -1.6653345369377348e-14
    ],
    [
      -0.3550394367365114,
      5.277028813921447e-15,
      [
        0.0,
        0.0,
        0.0,
        0.0,
        0.0,
        0.0
      ],
      -11.390149474439127
    ],
    [
      0.5294011900056361,
      0.0,
      [
        0.0,
        0.0,
        0.0,
        0.0,
        0.0,
        0.0
      ],
      -4.896684683276127
    ],
    [
      -1.9789603190056624,
      2.3175905639050143e-14,
      [
        0.0,
        0.0,
        0.0,
        0.0,
        0.0,
        0.0
      ],
      19.531834654734574
    ],
    [
      0.18066492136446707,
      -2.770353391134961e-15,
      [
        0.0,
        0.0,
        0.0,
        0.0,
        0.0,
        0.0
      ],
      1.1767193380176615
    ],
    [
      1.6769645020790744,
      -2.4730217873525362e-14,
      [
        0.0,
        0.0,
        0.0,
        0.0,
        0.0,
        0.0
      ],
      1.5702189012118615
    ],
    [
      2.6312001522062163,
      4.5276282722994665e-14,
      [
        0.0,
        0.0,
        0.0,
        0.0,
        0.0,
        0.0
      ],
      -1.857351418499409e-08
    ],
    [
      0.0,
      0.0,
      [
        0.0,
        0.0,
        0.0,
        0.0,
        0.0,
        0.0
      ],
      0.0
    ],
    [
      0.0,
      0.0,
      [
        0.0,
        0.0,
        0.0,
        0.0,
        0.0,
        0.0
      ],
      0.0
    ],
    [
      -1.0035883320028209e-06,
      -1.734723475976807e-18,
      [
        0.0,
        0.0,
        0.0,
        0.0,
        0.0,
        0.0
      ],
      -0.007833769624496528
    ],
    [
      2.3067679208131984e-06,
      1.734723475976807e-18,
      [
        0.0,
        0.0,
        0.0,
        0.0,
        0.0,
        0.0
      ],
      0.007833769624496528
    ],
    [
      0.0,
      0.0,
      [
        0.0,
        0.0,
        0.0,
        0.0,
        0.0,
        0.0
      ],
      0.0
    ]
  ],
  "seed": 6,
  "task": "pushing"
}