{
  "object": [
    [
      0.3673362808754054,
      0.03200877834445948,
      1.2646948017774609
    ],
    [
      0.09772584049887983,
      0.03642831615878451,
      0.33669251848619014,
      0.9358209154940115
    ]
  ],
  "arm": [
    [
      0.0,
      0.0,
      1.25
    ],
    [
      0.0,
      0.0,
      0.0,
      1.0
    ]
  ],
  "joints": [
    [
      0.00226600287121888,
      -4.423544863740858e-17,
      [
        0.0,
        0.0,
        0.0,
        0.0,
        0.0,
        0.0
      ],
      1.0798653637955624e-15
    ],
    [
      -0.9748987315356097,
      1.3183898417423734e-14,
      [
        0.0,
        0.0,
        0.0,
        0.0,
        0.0,
        0.0
      ],
      2.408839448355637
    ],
    [
      0.07530411939137874,
      0.0,
      [
        0.0,
        0.0,
        0.0,
        0.0,
        0.0,
        0.0
      ],
      -2.204100096130139
    ],
    [
      -2.4581109645100394,
      4.468647674116255e-14,
      [
        0.0,
        0.0,
        0.0,
        0.0,
        0.0,
        0.0
      ],
      18.846111216180287
    ],
    [
      0.06252907802139128,
      -1.4137996329210978e-15,
      [
        0.0,
        0.0,
        0.0,
        0.0,
        0.0,
        0.0
      ],
      1.1728270225661592
    ],
    [
      1.4851542617300297,
      -2.145505995088115e-14,
      [
        0.0,
        0.0,
        0.0,
        0.0,
        0.0,
        0.0
      ],
      1.5554579032236955
    ],
    [
      0.8984794226179991,
      1.1362438767648086e-14,
      [
        0.0,
        0.0,
        0.0,
        0.0,
        0.0,
        0.0
      ],
      2.022686725142858e-09
    ],
    [
      0.0,
      0.0,
      [
        0.0,
        0.0,
        0.0,
        0.0,
        0.0,
        0.0
      ],
      0.0
    ],
    [
      0.0,
      0.0,
      [
        0.0,
        0.0,
        0.0,
        0.0,
        0.0,
        0.0
      ],
      0.0
    ],
    [
      -1.4410216703385448e-06,
      0.0,
      [
        0.0,
        0.0,
        0.0,
        0.0,
        0.0,
        0.0
      ],
      -0.0002933545198050133
    ],
    [
      3.1069395889759805e-06,
      -2.168404344971009e-19,
      [
        0.0,
        0.0,
        0.0,
        0.0,
        0.0,
        0.0
      ],
      4.1291111892805075e-05
    ],
    [
      0.0,
      0.0,
      [
        0.0,
        0.0,
        0.0,
        0.0,
        0.0,
        0.0
      ],
      0.0
    ]
  ],
  "seed": 7,
  "task": "pushing"
}