{
  "object": [
    [
      0.3503992295416299,
      0.021984550943910067,
      1.2724734538392812
    ],
    [
      0.06433916955949182,
      -0.17797405659013346,
      0.33170004625067234,
      0.9242081939468773
    ]
  ],
  "arm": [
    [
      0.0,
      0.0,
      1.25
    ],
    [
      0.0,
      0.0,
      0.0,
      1.0
    ]
  ],
  "joints": [
    [
      0.07349013162172009,
      1.5080710118187124e-15,
      [
        0.0,
        0.0,
        0.0,
        0.0,
        0.0,
        0.0
      ],
      1.1546753136970622e-16
    ],
    [
      -0.93217691364197,
      -1.2365108936762681e-14,
      [
        0.0,
        0.0,
        0.0,
        0.0,
        0.0,
        0.0
      ],
      1.3964836158164728
    ],
    [
      -0.12590293225130772,
      -3.3306690738754696e-15,
      [
        0.0,
        0.0,
        0.0,
        0.0,
        0.0,
        0.0
      ],
      1.5454607136090728
    ],
    [
      -2.4142624851179173,
      -4.468647674116255e-14,
      [
        0.0,
        0.0,
        0.0,
        0.0,
        0.0,
        0.0
      ],
      18.813504151523784
    ],
    [
      -0.10119429153765316,
      -1.4675760606763788e-15,
      [
        0.0,
        0.0,
        0.0,
        0.0,
        0.0,
        0.0
      ],
      1.173296672148436
    ],
    [
      1.487825633814744,
      -2.525757381022231e-14,
      [
        0.0,
        0.0,
        0.0,
        0.0,
        0.0,
        0.0
      ],
      1.5572181981960924
    ],
    [
      0.1066550008560117,
      1.4883927423881005e-15,
      [
        0.0,
        0.0,
        0.0,
        0.0,
        0.0,
        0.0
      ],
      -5.75672200338849e-10
    ],
    [
      0.0,
      0.0,
      [
        0.0,
        0.0,
        0.0,
        0.0,
        0.0,
        0.0
      ],
      0.0
    ],
    [
      0.0,
      0.0,
      [
        0.0,
        0.0,
        0.0,
        0.0,
        0.0,
        0.0
      ],
      0.0
    ],
    [
      1.519426967759067e-07,
      4.336808689942018e-19,
      [
        0.0,
        0.0,
        0.0,
        0.0,
        0.0,
        0.0
      ],
      0.0007989830099267557
    ],
    [
      -3.106906577239633e-07,
      0.0,
      [
        0.0,
        0.0,
        0.0,
        0.0,
        0.0,
        0.0
      ],
      -0.0007989830099267687
    ],
    [
      0.0,
      0.0,
      [
        0.0,
        0.0,
        0.0,
        0.0,
        0.0,
        0.0
      ],
      0.0
    ]
  ],
  "seed": 7,
  "task": "pushing"
}