{
  "object": [
    [
      0.44898384521360213,
      0.005662150532515014,
      1.269877075291523
    ],
    [
      0.055637987166046905,
      0.024433253417777065,
      0.9977844456255479,
      0.027085615725906863
    ]
  ],
  "arm": [
    [
      0.0,
      0.0,
      1.25
    ],
    [
      0.0,
      0.0,
      0.0,
      1.0
    ]
  ],
  "joints": [
    [
      -0.019259882449007865,
      -3.937822290467352e-16,
      [
        0.0,
        0.0,
        0.0,
        0.0,
        0.0,
        0.0
      ],
      -1.4994516045474526e-15
    ],
    [
      -0.6861077377769254,
      -1.1178558079194545e-14,
      [
        0.0,
        0.0,
        0.0,
        0.0,
        0.0,
        0.0
      ],
      -5.433158065935122
    ],
    [
      -0.10259538699084751,
      1.3322676295501878e-15,
      [
        0.0,
        0.0,
        0.0,
        0.0,
        0.0,
        0.0
      ],
      0.9679985496060985
    ],
    [
      -2.2799277372091553,
      -4.3798298321462426e-14,
      [
        0.0,
        0.0,
        0.0,
        0.0,
        0.0,
        0.0
      ],
      19.47565523137968
    ],
    [
      -0.0645579579822803,
      -1.5577816814271728e-15,
      [
        0.0,
        0.0,
        0.0,
        0.0,
        0.0,
        0.0
      ],
      1.177463860309485
    ],
    [
      1.5981875817215205,
      -2.42861286636753e-14,
      [
        0.0,
        0.0,
        0.0,
        0.0,
        0.0,
        0.0
      ],
      1.557790284570209
    ],
    [
      0.519482965082338,
      1.1600963245594897e-14,
      [
        0.0,
        0.0,
        0.0,
        0.0,
        0.0,
        0.0
      ],
      5.8792046678615185e-09
    ],
    [
      0.0,
      0.0,
      [
        0.0,
        0.0,
        0.0,
        0.0,
        0.0,
        0.0
      ],
      0.0
    ],
    [
      0.0,
      0.0,
      [
        0.0,
        0.0,
        0.0,
        0.0,
        0.0,
        0.0
      ],
      0.0
    ],
    [
      -1.0095897637657464e-06,
      1.3010426069826053e-18,
      [
        0.0,
        0.0,
        0.0,
        0.0,
        0.0,
        0.0
      ],
      -0.33128653786651024
    ],
    [
      2.183237894905745e-06,
      -1.3010426069826053e-18,
      [
        0.0,
        0.0,
        0.0,
        0.0,
        0.0,
        0.0
      ],
      -0.00010286815276017462
    ],
    [
      0.0,
      0.0,
      [
        0.0,
        0.0,
        0.0,
        0.0,
        0.0,
        0.0
      ],
      0.0
    ]
  ],
  "seed": 4,
  "task": "hammering"
}