{
  "object": [
    [
      0.39570962194002196,
      -0.046943571349319306,
      1.2687776731234033
    ],
    [
      0.049502186702756794,
      0.03258483310293305,
      0.9371697488436922,
      0.3438031762732136
    ]
  ],
  "arm": [
    [
      0.0,
      0.0,
      1.25
    ],
    [
      0.0,
      0.0,
      0.0,
      1.0
    ]
  ],
  "joints": [
    [
      -0.09285529405800551,
      1.41661855856956e-15,
      [
        0.0,
        0.0,
        0.0,
        0.0,
        0.0,
        0.0
      ],
      -2.2573089231148202e-15
    ],
    [
      -0.7920011723335934,
      1.2795320358804929e-14,
      [
        0.0,
        0.0,
        0.0,
        0.0,
        0.0,
        0.0
      ],
      -2.3096907537436078
    ],
    [
      -0.15409132568459444,
      0.0,
      [
        0.0,
        0.0,
        0.0,
        0.0,
        0.0,
        0.0
      ],
      1.9191697393815306
    ],
    [
      -2.3345331373926084,
      4.884981308350689e-14,
      [
        0.0,
        0.0,
        0.0,
        0.0,
        0.0,
        0.0
      ],
      19.163450332143917
    ],
    [
      -0.10893157857017392,
      -1.474514954580286e-15,
      [
        0.0,
        0.0,
        0.0,
        0.0,
        0.0,
        0.0
      ],
      1.1778712169564693
    ],
    [
      1.5497533248954425,
      -2.3869795029440866e-14,
      [
        0.0,
        0.0,
        0.0,
        0.0,
        0.0,
        0.0
      ],
      1.5565923174490264
    ],
    [
      0.5313099277806721,
      1.226796442210798e-14,
      [
        0.0,
        0.0,
        0.0,
        0.0,
        0.0,
        0.0
      ],
      4.051028984920074e-09
    ],
    [
      0.0,
      0.0,
      [
        0.0,
        0.0,
        0.0,
        0.0,
        0.0,
        0.0
      ],
      0.0
    ],
    [
      0.0,
      0.0,
      [
        0.0,
        0.0,
        0.0,
        0.0,
        0.0,
        0.0
      ],
      0.0
    ],
    [
      -1.0597526778160963e-06,
      0.0,
      [
        0.0,
        0.0,
        0.0,
        0.0,
        0.0,
        0.0
      ],
      -0.30605975476324887
    ],
    [
      2.292155105383474e-06,
      0.0,
      [
        0.0,
        0.0,
        0.0,
        0.0,
        0.0,
        0.0
      ],
      0.00025001123759286646
    ],
    [
      0.0,
      0.0,
      [
        0.0,
        0.0,
        0.0,
        0.0,
        0.0,
        0.0
      ],
      0.0
    ]
  ],
  "seed": 2,
  "task": "hammering"
}