{
  "object": [
    [
      0.44675267309001415,
      0.004739716237356153,
      1.2676972807705704
    ],
    [
      -1.574816412116796e-05,
      -2.499996012508644e-05,
      -0.02091877393953973,
      0.9997811780704134
    ]
  ],
  "arm": [
    [
      0.0,
      0.0,
      1.25
    ],
    [
      0.0,
      0.0,
      0.0,
      1.0
    ]
  ],
  "joints": [
    [
      0.28538043556518833,
      5.8364771349239675e-15,
      [
        0.0,
        0.0,
        0.0,
        0.0,
        0.0,
        0.0
      ],
      -4.891920202254596e-15
    ],
    [
      -0.35220956345224796,
      5.814793091474257e-15,
      [
        0.0,
        0.0,
        0.0,
        0.0,
        0.0,
        0.0
      ],
      -15.082574153997538
    ],
    [
      -0.2278857844438568,
      1.734723475976807e-18,
      [
        0.0,
        0.0,
        0.0,
        0.0,
        0.0,
        0.0
      ],
      1.6934582274936223
    ],
    [
      -2.045177113502927,
      5.240252676230739e-14,
      [
        0.0,
        0.0,
        0.0,
        0.0,
        0.0,
        0.0
      ],
      19.835869225826062
    ],
    [
      -0.07955831158246186,
      -1.4988010832439613e-15,
      [
        0.0,
        0.0,
        0.0,
        0.0,
        0.0,
        0.0
      ],
      1.165968160050023
    ],
    [
      1.7060328182922362,
      -2.5757174171303632e-14,
      [
        0.0,
        0.0,
        0.0,
        0.0,
        0.0,
        0.0
      ],
      1.5632274324750965
    ],
    [
      -0.6667262924994519,
      1.2932363513407097e-14,
      [
        0.0,
        0.0,
        0.0,
        0.0,
        0.0,
        0.0
      ],
      2.7627515997597635e-10
    ],
    [
      0.0,
      0.0,
      [
        0.0,
        0.0,
        0.0,
        0.0,
        0.0,
        0.0
      ],
      0.0
    ],
    [
      0.0,
      0.0,
      [
        0.0,
        0.0,
        0.0,
        0.0,
        0.0,
        0.0
      ],
      0.0
    ],
    [
      6.660120159504229e-07,
      1.734723475976807e-18,
      [
        0.0,
        0.0,
        0.0,
        0.0,
        0.0,
        0.0
      ],
      0.005037303016246649
    ],
    [
      -4.0475644820546135e-07,
      -1.3010426069826053e-18,
      [
        0.0,
        0.0,
        0.0,
        0.0,
        0.0,
        0.0
      ],
      -0.00503730301624663
    ],
    [
      0.0,
      0.0,
      [
        0.0,
        0.0,
        0.0,
        0.0,
        0.0,
        0.0
      ],
      0.0
    ]
  ],
  "seed": 4,
  "task": "hammering"
}