{
  "object": [
    [
      0.4467388716783094,
      0.004708520008863535,
      1.2675517439196267
    ],
    [
      -3.874736946346869e-05,
      2.1328733292573384e-06,
      0.9997612491205715,
      0.021850474845336382
    ]
  ],
  "arm": [
    [
      0.0,
      0.0,
      1.25
    ],
    [
      0.0,
      0.0,
      0.0,
      1.0
    ]
  ],
  "joints": [
    [
      0.3653194434476444,
      6.035102972923312e-15,
      [
        0.0,
        0.0,
        0.0,
        0.0,
        0.0,
        0.0
      ],
      1.5612511283791264e-15
    ],
    [
      -0.3825771138828704,
      5.946632075648495e-15,
      [
        0.0,
        0.0,
        0.0,
        0.0,
        0.0,
        0.0
      ],
      -13.57560873012606
    ],
    [
      -0.3245220975865369,
      0.0,
      [
        0.0,
        0.0,
        0.0,
        0.0,
        0.0,
        0.0
      ],
      2.731627517726528
    ],
    [
      -2.0597048582592032,
      4.6407322429331543e-14,
      [
        0.0,
        0.0,
        0.0,
        0.0,
        0.0,
        0.0
      ],
      19.734787196141035
    ],
    [
      -0.1216436665133952,
      -1.4779844015322396e-15,
      [
        0.0,
        0.0,
        0.0,
        0.0,
        0.0,
        0.0
      ],
      1.1661562675354944
    ],
    [
      1.700703320320411,
      -2.6201263381153694e-14,
      [
        0.0,
        0.0,
        0.0,
        0.0,
        0.0,
        0.0
      ],
      1.565226145422254
    ],
    [
      -0.5794206263061312,
      1.1005085731596864e-14,
      [
        0.0,
        0.0,
        0.0,
        0.0,
        0.0,
        0.0
      ],
      8.178430589006469e-11
    ],
    [
      0.0,
      0.0,
      [
        0.0,
        0.0,
        0.0,
        0.0,
        0.0,
        0.0
      ],
      0.0
    ],
    [
      0.0,
      0.0,
      [
        0.0,
        0.0,
        0.0,
        0.0,
        0.0,
        0.0
      ],
      0.0
    ],
    [
      6.047026514965395e-07,
      -1.734723475976807e-18,
      [
        0.0,
        0.0,
        0.0,
        0.0,
        0.0,
        0.0
      ],
      0.006289115254890226
    ],
    [
      -3.7176903156581216e-07,
      1.3010426069826053e-18,
      [
        0.0,
        0.0,
        0.0,
        0.0,
        0.0,
        0.0
      ],
      -0.006289115254890297
    ],
    [
      0.0,
      0.0,
      [
        0.0,
        0.0,
        0.0,
        0.0,
        0.0,
        0.0
      ],
      0.0
    ]
  ],
  "seed": 4,
  "task": "hammering"
}