{
  "object": [
    [
      0.4069507148751942,
      0.02215554783584377,
      1.268777673110534
    ],
    [
      0.04809640128364043,
      0.03462620540331319,
      0.950725802908963,
      0.30431597027766727
    ]
  ],
  "arm": [
    [
      0.0,
      0.0,
      1.25
    ],
    [
      0.0,
      0.0,
      0.0,
      1.0
    ]
  ],
  "joints": [
    [
      0.17402510088367723,
      3.290336753059009e-15,
      [
        0.0,
        0.0,
        0.0,
        0.0,
        0.0,
        0.0
      ],
      -1.951563910473908e-15
    ],
    [
      -0.4863073823091223,
      5.870304242705515e-15,
      [
        0.0,
        0.0,
        0.0,
        0.0,
        0.0,
        0.0
      ],
      -11.424030845482235
    ],
    [
      -0.11284122193419714,
      0.0,
      [
        0.0,
        0.0,
        0.0,
        0.0,
        0.0,
        0.0
      ],
      0.8766705611530067
    ],
    [
      -2.169920889575864,
      4.754530102957233e-14,
      [
        0.0,
        0.0,
        0.0,
        0.0,
        0.0,
        0.0
      ],
      19.826692852780877
    ],
    [
      -0.05320512006591011,
      -7.494005416219807e-16,
      [
        0.0,
        0.0,
        0.0,
        0.0,
        0.0,
        0.0
      ],
      1.1690849214568837
    ],
    [
      1.6886671160166122,
      -2.3148150063434514e-14,
      [
        0.0,
        0.0,
        0.0,
        0.0,
        0.0,
        0.0
      ],
      1.559045446884051
    ],
    [
      -0.04043922880865166,
      7.840950111415168e-16,
      [
        0.0,
        0.0,
        0.0,
        0.0,
        0.0,
        0.0
      ],
      2.263381189827711e-10
    ],
    [
      0.0,
      0.0,
      [
        0.0,
        0.0,
        0.0,
        0.0,
        0.0,
        0.0
      ],
      0.0
    ],
    [
      0.0,
      0.0,
      [
        0.0,
        0.0,
        0.0,
        0.0,
        0.0,
        0.0
      ],
      0.0
    ],
    [
      -4.0817354292010216e-08,
      2.6020852139652106e-18,
      [
        0.0,
        0.0,
        0.0,
        0.0,
        0.0,
        0.0
      ],
      -1.0197634771613044
    ],
    [
      1.0309693175257952e-07,
      -1.734723475976807e-18,
      [
        0.0,
        0.0,
        0.0,
        0.0,
        0.0,
        0.0
      ],
      -0.0019964202397403812
    ],
    [
      0.0,
      0.0,
      [
        0.0,
        0.0,
        0.0,
        0.0,
        0.0,
        0.0
      ],
      0.0
    ]
  ],
  "seed": 0,
  "task": "hammering"
}