{
  "object": [
    [
      0.37069316422433013,
      0.04075538720267036,
      1.2660634163333155
    ],
    [
      -0.10359714747700079,
      0.06485624126859864,
      0.8079849384921238,
      0.5763867088795651
    ]
  ],
  "arm": [
    [
      0.0,
      0.0,
      1.25
    ],
    [
      0.0,
      0.0,
      0.0,
      1.0
    ]
  ],
  "joints": [
    [
      0.07333960632567194,
      1.4862243380431295e-15,
      [
        0.0,
        0.0,
        0.0,
        0.0,
        0.0,
        0.0
      ],
      1.6263032587282567e-15
    ],
    [
      -0.6047171055820489,
      1.1400602684119576e-14,
      [
        0.0,
        0.0,
        0.0,
        0.0,
        0.0,
        0.0
      ],
      -8.01572859006517
    ],
    [
      0.01216307463566647,
      0.0,
      [
        0.0,
        0.0,
        0.0,
        0.0,
        0.0,
        0.0
      ],
      -0.7196125844056162
    ],
    [
      -2.2782568741393843,
      -5.004330283497893e-14,
      [
        0.0,
        0.0,
        0.0,
        0.0,
        0.0,
        0.0
      ],
      19.820717336043213
    ],
    [
      0.006924738120974631,
      -8.326672684688674e-17,
      [
        0.0,
        0.0,
        0.0,
        0.0,
        0.0,
        0.0
      ],
      1.1709500560836716
    ],
    [
      1.675073578927809,
      -2.2315482794965646e-14,
      [
        0.0,
        0.0,
        0.0,
        0.0,
        0.0,
        0.0
      ],
      1.5572224934207632
    ],
    [
      0.5572237907682647,
      1.1638137827583994e-14,
      [
        0.0,
        0.0,
        0.0,
        0.0,
        0.0,
        0.0
      ],
      3.706395024808401e-09
    ],
    [
      0.0,
      0.0,
      [
        0.0,
        0.0,
        0.0,
        0.0,
        0.0,
        0.0
      ],
      0.0
    ],
    [
      0.0,
      0.0,
      [
        0.0,
        0.0,
        0.0,
        0.0,
        0.0,
        0.0
      ],
      0.0
    ],
    [
      -8.204274911650131e-07,
      -4.336808689942018e-19,
      [
        0.0,
        0.0,
        0.0,
        0.0,
        0.0,
        0.0
      ],
      -0.2771133665655575
    ],
    [
      1.7732201238123707e-06,
      0.0,
      [
        0.0,
        0.0,
        0.0,
        0.0,
        0.0,
        0.0
      ],
      -0.00035878917879567313
    ],
    [
      0.0,
      0.0,
      [
        0.0,
        0.0,
        0.0,
        0.0,
        0.0,
        0.0
      ],
      0.0
    ]
  ],
  "seed": 5,
  "task": "hammering"
}