{
  "object": [
    [
      0.419795500420272,
      0.03570584755356158,
      1.2622090528422802
    ],
    [
      0.04017445379145336,
      -0.0007035503388041468,
      0.2238577640520367,
      0.9737932120081254
    ]
  ],
  "arm": [
    [
      0.0,
      0.0,
      1.25
    ],
    [
      0.0,
      0.0,
      0.0,
      1.0
    ]
  ],
  "joints": [
    [
      0.073895029264747,
      1.5686237031520278e-15,
      [
        0.0,
        0.0,
        0.0,
        0.0,
        0.0,
        0.0
      ],
      1.1384122811097797e-17
    ],
    [
      -0.497200462684854,
      6.591949208711867e-15,
      [
        0.0,
        0.0,
        0.0,
        0.0,
        0.0,
        0.0
      ],
      -11.13421715175342
    ],
    [
      -0.03534952507394761,
      0.0,
      [
        0.0,
        0.0,
        0.0,
        0.0,
        0.0,
        0.0
      ],
      -0.03679426733269643
    ],
    [
      -2.16939205058615,
      4.2771342023684156e-14,
      [
        0.0,
        0.0,
        0.0,
        0.0,
        0.0,
        0.0
      ],
      19.813434519675916
    ],
    [
      -0.016949529203945303,
      -3.95516952522712e-16,
      [
        0.0,
        0.0,
        0.0,
        0.0,
        0.0,
        0.0
      ],
      1.1711202928381386
    ],
    [
      1.6748524741305264,
      -2.450817326860033e-14,
      [
        0.0,
        0.0,
        0.0,
        0.0,
        0.0,
        0.0
      ],
      1.5587591704843848
    ],
    [
      0.42715430200154536,
      5.3507545616504615e-15,
      [
        0.0,
        0.0,
        0.0,
        0.0,
        0.0,
        0.0
      ],
      5.836202303903396e-09
    ],
    [
      0.0,
      0.0,
      [
        0.0,
        0.0,
        0.0,
        0.0,
        0.0,
        0.0
      ],
      0.0
    ],
    [
      0.0,
      0.0,
      [
        0.0,
        0.0,
        0.0,
        0.0,
        0.0,
        0.0
      ],
      0.0
    ],
    [
      -8.324030306732955e-07,
      0.0,
      [
        0.0,
        0.0,
        0.0,
        0.0,
        0.0,
        0.0
      ],
      -0.47253639067039477
    ],
    [
      1.8014589962822455e-06,
      -4.336808689942018e-19,
      [
        0.0,
        0.0,
        0.0,
        0.0,
        0.0,
        0.0
      ],
      -0.0008340094051606842
    ],
    [
      0.0,
      0.0,
      [
        0.0,
        0.0,
        0.0,
        0.0,
        0.0,
        0.0
      ],
      0.0
    ]
  ],
  "seed": 3,
  "task": "grasping"
}