{
  "object": [
    [
      0.35104998207269217,
      0.00015376034687740575,
      1.2637329560050339
    ],
    [
      -0.379685551441529,
      0.9251156046738425,
      -3.8813035936903134e-06,
      6.544928360028804e-07
    ]
  ],
  "arm": [
    [
      0.0,
      0.0,
      1.25
    ],
    [
      0.0,
      0.0,
      0.0,
      1.0
    ]
  ],
  "joints": [
    [
      -0.1521434563993759,
      2.985459102156085e-15,
      [
        0.0,
        0.0,
        0.0,
        0.0,
        0.0,
        0.0
      ],
      -4.111294638065033e-15
    ],
    [
      -1.1298415854684163,
      2.621514116896151e-14,
      [
        0.0,
        0.0,
        0.0,
        0.0,
        0.0,
        0.0
      ],
      6.486432717493296
    ],
    [
      0.24909408432630004,
      -2.6645352591003757e-15,
      [
        0.0,
        0.0,
        0.0,
        0.0,
        0.0,
        0.0
      ],
      -5.686203751211457
    ],
    [
      -2.5337023028066032,
      -4.782285678572862e-14,
      [
        0.0,
        0.0,
        0.0,
        0.0,
        0.0,
        0.0
      ],
      17.89389076510832
    ],
    [
      0.22802479515333987,
      -2.7269853042355408e-15,
      [
        0.0,
        0.0,
        0.0,
        0.0,
        0.0,
        0.0
      ],
      1.164911001711631
    ],
    [
      1.420487331914047,
      2.1815882433884326e-14,
      [
        0.0,
        0.0,
        0.0,
        0.0,
        0.0,
        0.0
      ],
      1.5555053304400677
    ],
    [
      1.2398629352173307,
      2.6405960751318958e-14,
      [
        0.0,
        0.0,
        0.0,
        0.0,
        0.0,
        0.0
      ],
      1.3767219168066974e-09
    ],
    [
      0.0,
      0.0,
      [
        0.0,
        0.0,
        0.0,
        0.0,
        0.0,
        0.0
      ],
      0.0
    ],
    [
      0.0,
      0.0,
      [
        0.0,
        0.0,
        0.0,
        0.0,
        0.0,
        0.0
      ],
      0.0
    ],
    [
      -2.323936624751353e-06,
      1.6263032587282567e-18,
      [
        0.0,
        0.0,
        0.0,
        0.0,
        0.0,
        0.0
      ],
      -0.0006999001104790464
    ],
    [
      5.152715458739725e-06,
      -1.6263032587282567e-18,
      [
        0.0,
        0.0,
        0.0,
        0.0,
        0.0,
        0.0
      ],
      0.0006999001104790806
    ],
    [
      0.0,
      0.0,
      [
        0.0,
        0.0,
        0.0,
        0.0,
        0.0,
        0.0
      ],
      0.0
    ]
  ],
  "seed": 9,
  "task": "grasping"
}