{
  "object": [
    [
      0.37506029473204455,
      0.04168326347683546,
      1.3178208250061243
    ],
    [
      0.01124123315596955,
      -0.004121193899460054,
      0.21323614899804325,
      0.9769273233964032
    ]
  ],
  "arm": [
    [
      0.0,
      0.0,
      1.25
    ],
    [
      0.0,
      0.0,
      0.0,
      1.0
    ]
  ],
  "joints": [
    [
      -0.1652914951253787,
      3.301395615218361e-15,
      [
        0.0,
        0.0,
        0.0,
        0.0,
        0.0,
        0.0
      ],
      9.62771529167128e-16
    ],
    [
      -0.4171597197014761,
      5.766220834146907e-15,
      [
        0.0,
        0.0,
        0.0,
        0.0,
        0.0,
        0.0
      ],
      -11.769213990876638
    ],
    [
      0.15074280349981903,
      -2.6645352591003757e-15,
      [
        0.0,
        0.0,
        0.0,
        0.0,
        0.0,
        0.0
      ],
      -1.9972601989187277
    ],
    [
      -1.8437746901123735,
      2.2121193765656244e-14,
      [
        0.0,
        0.0,
        0.0,
        0.0,
        0.0,
        0.0
      ],
      18.499961533333238
    ],
    [
      0.06208203496238675,
      -7.077671781985373e-16,
      [
        0.0,
        0.0,
        0.0,
        0.0,
        0.0,
        0.0
      ],
      1.1668372161111604
    ],
    [
      1.451979128949012,
      -2.1593837828959295e-14,
      [
        0.0,
        0.0,
        0.0,
        0.0,
        0.0,
        0.0
      ],
      1.5896337523656436
    ],
    [
      0.9481152123316675,
      1.1395398513691646e-14,
      [
        0.0,
        0.0,
        0.0,
        0.0,
        0.0,
        0.0
      ],
      4.7189468405464154e-08
    ],
    [
      0.0,
      0.0,
      [
        0.0,
        0.0,
        0.0,
        0.0,
        0.0,
        0.0
      ],
      0.0
    ],
    [
      0.0,
      0.0,
      [
        0.0,
        0.0,
        0.0,
        0.0,
        0.0,
        0.0
      ],
      0.0
    ],
    [
      -7.428642665130578e-07,
      8.673617379884035e-19,
      [
        0.0,
        0.0,
        0.0,
        0.0,
        0.0,
        0.0
      ],
      -0.004055491708819352
    ],
    [
      1.6012480420852623e-06,
      -8.673617379884035e-19,
      [
        0.0,
        0.0,
        0.0,
        0.0,
        0.0,
        0.0
      ],
      0.0038954477104703776
    ],
    [
      0.0,
      0.0,
      [
        0.0,
        0.0,
        0.0,
        0.0,
        0.0,
        0.0
      ],
      0.0
    ]
  ],
  "seed": 5,
  "task": "grasping"
}